packagedummy/__init__.py
packagedummy/main.py
packagedummy-0.0.2.data/scripts/packagedummy_cli
packagedummy-0.0.2.dist-info/METADATA
packagedummy-0.0.2.dist-info/WHEEL
packagedummy-0.0.2.dist-info/top_level.txt
packagedummy-0.0.2.dist-info/RECORD
